netzoo_porcupine/__init__.py
netzoo_porcupine/init.py
netzoo_porcupine/pca_pathway.py
netzoo_porcupine/pca_random.py
netzoo_porcupine/pca_scores.py
netzoo_porcupine/porcupine.py
netzoo_porcupine/run_pca.py
netzoo_porcupine/select_visualize_clusters.py
netzoo_porcupine-1.0.3.dist-info/LICENSE
netzoo_porcupine-1.0.3.dist-info/METADATA
netzoo_porcupine-1.0.3.dist-info/WHEEL
netzoo_porcupine-1.0.3.dist-info/top_level.txt
netzoo_porcupine-1.0.3.dist-info/RECORD
