Metadata-Version: 2.1
Name: netzoo_porcupine
Version: 1.0.3
Summary: A package implementing a Principal Components Analysis (PCA)-based approach to identify biological pathways driving inter-tumour heterogeneity in gene regulatory networks.
Author-email: Rosalie Coulon <rosalie.coulon@hotmail.fr>
Maintainer-email: Ladislav Hovan <ladislav.hovan@ncmm.uio.no>
Project-URL: homepage, https://github.com/rosalie49/PORCUPINE
Classifier: Programming Language :: Python :: 3
Classifier: License :: OSI Approved :: MIT License
Classifier: Operating System :: OS Independent
Requires-Python: >=3.8
License-File: LICENSE
Requires-Dist: pyreadr
Requires-Dist: pandas
Requires-Dist: numpy
Requires-Dist: scikit-learn
Requires-Dist: scipy
Requires-Dist: yellowbrick
Requires-Dist: seaborn
Requires-Dist: matplotlib
